edutk/__init__.py
edutk/edutk.py
edutk-0.1.3.dist-info/LICENSE
edutk-0.1.3.dist-info/METADATA
edutk-0.1.3.dist-info/WHEEL
edutk-0.1.3.dist-info/top_level.txt
edutk-0.1.3.dist-info/RECORD
