Metadata-Version: 2.1
Name: edutk
Version: 0.1.3
Summary: Toolkit to make modern exercises for programming tutorials.
Home-page: https://github.com/epeios-q37/edutk-python
Author: Claude SIMON
License: UNKNOWN
Keywords: education,tutorial,programming,exercise,Atlas toolkit
Platform: UNKNOWN
Classifier: Development Status :: 4 - Beta
Classifier: Environment :: Web Environment
Classifier: Intended Audience :: Education
Classifier: Intended Audience :: Other Audience
Classifier: License :: OSI Approved :: MIT License 
Classifier: Operating System :: OS Independent
Classifier: Programming Language :: Python :: 2
Classifier: Programming Language :: Python :: 3
Classifier: Topic :: Education
Requires-Dist: atlastk
